atikin_logger/__init__.py
atikin_logger/logger.py
atikin_logger-0.1.0.dist-info/LICENSE
atikin_logger-0.1.0.dist-info/METADATA
atikin_logger-0.1.0.dist-info/WHEEL
atikin_logger-0.1.0.dist-info/top_level.txt
atikin_logger-0.1.0.dist-info/RECORD
