Metadata-Version: 2.1
Name: atikin-logger
Version: 0.1.0
Summary: A lightweight and beginner-friendly Python logging library
Home-page: https://github.com/atikinverse/atikin-logger
Author: Your Name
Author-email: your.email@example.com
Keywords: logging,logger,simple,lightweight,colored-output
Classifier: Development Status :: 4 - Beta
Classifier: Intended Audience :: Developers
Classifier: License :: OSI Approved :: MIT License
Classifier: Operating System :: OS Independent
Classifier: Programming Language :: Python :: 3
Classifier: Programming Language :: Python :: 3.6
Classifier: Programming Language :: Python :: 3.7
Classifier: Programming Language :: Python :: 3.8
Classifier: Programming Language :: Python :: 3.9
Classifier: Programming Language :: Python :: 3.10
Classifier: Programming Language :: Python :: 3.11
Classifier: Topic :: Software Development :: Libraries :: Python Modules
Classifier: Topic :: System :: Logging
Requires-Python: >=3.6
License-File: LICENSE
